mldock/__init__.py
mldock/__main__.py
mldock/__version__.py
mldock/log.py
mldock/terminal.py
mldock/api/__init__.py
mldock/api/assets.py
mldock/api/bash.py
mldock/api/local.py
mldock/api/logs.py
mldock/api/packages.py
mldock/api/predict.py
mldock/api/registry.py
mldock/api/runner.py
mldock/api/templates.py
mldock/command/__init__.py
mldock/command/configure.py
mldock/command/datasets.py
mldock/command/local.py
mldock/command/models.py
mldock/command/packages.py
mldock/command/projects.py
mldock/command/registry.py
mldock/command/stages.py
mldock/command/templates.py
mldock/command/logs/__init__.py
mldock/command/logs/errors.py
mldock/command/logs/grok.py
mldock/command/logs/metrics.py
mldock/command/logs/params.py
mldock/config_managers/__init__.py
mldock/config_managers/cli.py
mldock/config_managers/core.py
mldock/config_managers/project.py
mldock/platform_helpers/__init__.py
mldock/platform_helpers/utils.py
mldock/platform_helpers/aws/__init__.py
mldock/platform_helpers/aws/auth.py
mldock/platform_helpers/docker/__init__.py
mldock/platform_helpers/docker/auth.py
mldock/platform_helpers/dockerhub/__init__.py
mldock/platform_helpers/dockerhub/auth.py
mldock/platform_helpers/gcp/__init__.py
mldock/platform_helpers/gcp/auth.py
mldock/platform_helpers/mldock/__init__.py
mldock/platform_helpers/mldock/errors.py
mldock/platform_helpers/mldock/utils.py
mldock/platform_helpers/mldock/asset_managers/__init__.py
mldock/platform_helpers/mldock/asset_managers/aws.py
mldock/platform_helpers/mldock/asset_managers/base.py
mldock/platform_helpers/mldock/asset_managers/gcp.py
mldock/platform_helpers/mldock/configuration/__init__.py
mldock/platform_helpers/mldock/configuration/container.py
mldock/platform_helpers/mldock/configuration/environment.py
mldock/platform_helpers/mldock/inference/__init__.py
mldock/platform_helpers/mldock/inference/content_decoders/__init__.py
mldock/platform_helpers/mldock/inference/content_decoders/numpy.py
mldock-0.9.2.dist-info/LICENSE
mldock-0.9.2.dist-info/METADATA
mldock-0.9.2.dist-info/WHEEL
mldock-0.9.2.dist-info/entry_points.txt
mldock-0.9.2.dist-info/top_level.txt
mldock-0.9.2.dist-info/RECORD
