Metadata-Version: 2.1
Name: mldock
Version: 0.9.2
Summary: A docker tool that helps put machine learning in places that empower ml developers
Home-page: https://github.com/mldock/mldock
Author: SheldonGrant
Author-email: sheldz.shakes.williams@gmail.com
License: UNKNOWN
Keywords: docker,machine learning,ml,ml services,MLaaS
Platform: UNKNOWN
Classifier: Development Status :: 2 - Pre-Alpha
Classifier: Intended Audience :: Developers
Classifier: License :: OSI Approved :: MIT License
Classifier: Programming Language :: Python :: 3.6
Requires-Python: >=3.6
Requires-Dist: future
Requires-Dist: environs
Requires-Dist: PyGithub
Provides-Extra: aws
Requires-Dist: boto3 ; extra == 'aws'
Requires-Dist: s3fs ; extra == 'aws'
Requires-Dist: pyarrow ; extra == 'aws'
Provides-Extra: cli
Requires-Dist: click ; extra == 'cli'
Requires-Dist: clickclick ; extra == 'cli'
Requires-Dist: docker ; extra == 'cli'
Requires-Dist: future ; extra == 'cli'
Requires-Dist: requests ; extra == 'cli'
Requires-Dist: boto3 ; extra == 'cli'
Requires-Dist: google-auth ; extra == 'cli'
Requires-Dist: appdirs ; extra == 'cli'
Requires-Dist: halo ; extra == 'cli'
Requires-Dist: PyYAML ; extra == 'cli'
Requires-Dist: pygrok ; extra == 'cli'
Requires-Dist: gcsfs ; extra == 'cli'
Requires-Dist: s3fs ; extra == 'cli'
Requires-Dist: pyarrow ; extra == 'cli'
Requires-Dist: wheel ; extra == 'cli'
Provides-Extra: gcp
Requires-Dist: google-cloud-storage ; extra == 'gcp'
Requires-Dist: google-api-python-client ; extra == 'gcp'
Requires-Dist: gcsfs ; extra == 'gcp'
Requires-Dist: pyarrow ; extra == 'gcp'
Provides-Extra: inference
Requires-Dist: pandas ; extra == 'inference'
Requires-Dist: numpy ; extra == 'inference'
Requires-Dist: protobuf (>=3.1) ; extra == 'inference'
Requires-Dist: Pillow ; extra == 'inference'
Provides-Extra: sagemaker
Requires-Dist: sagemaker-training ; extra == 'sagemaker'
Provides-Extra: testing
Requires-Dist: responses ; extra == 'testing'
Requires-Dist: dataclasses ; extra == 'testing'
